hack4u/__init__.py
hack4u/courses.py
hack4u/test.py
hack4u/utils.py
hack4uTestPG-0.1.0.dist-info/METADATA
hack4uTestPG-0.1.0.dist-info/WHEEL
hack4uTestPG-0.1.0.dist-info/top_level.txt
hack4uTestPG-0.1.0.dist-info/RECORD
