Metadata-Version: 2.1
Name: hack4uTestPG
Version: 0.1.0
Summary: Biblioteca para consultar cursos hack4u
Home-page: https://hack4u.io
Author: PG
